{
    "KPlugin": {
        "Authors": [
            {
                "Email": "matej@laitl.cz",
                "Name": "Matěj Laitl"
            }
        ],
        "Category": "Collection",
        "Description": "Plugin to use iPod-like devices as collections in Amarok",
        "EnabledByDefault": true,
        "Icon": "multimedia-player-apple-ipod",
        "Id": "amarok_collection-ipodcollection",
        "License": "GPL",
        "Name": "iPod, iPad & iPhone Collection",
        "ServiceTypes": [
            "Amarok/Plugin"
        ],
        "Version": "2.0"
    },
    "X-KDE-Amarok-authors": [
        "Matěj Laitl"
    ],
    "X-KDE-Amarok-email": [
        "matej@laitl.cz"
    ],
    "X-KDE-Amarok-framework-version": 74,
    "X-KDE-Amarok-name": "ipod-collection",
    "X-KDE-Amarok-rank": 100,
    "X-KDE-Amarok-version": 1
}
